adulib/__init__.py
adulib/asynchronous.py
adulib/caching.py
adulib/config.py
adulib/git.py
adulib/reflection.py
adulib/rest.py
adulib/algos/__init__.py
adulib/algos/_smart_dedup.py
adulib/algos/str_matching.py
adulib/cli/__init__.py
adulib/cli/base.py
adulib/cli/data_questionnaire.py
adulib/llm/__init__.py
adulib/llm/_utils.py
adulib/llm/base.py
adulib/llm/caching.py
adulib/llm/call_logging.py
adulib/llm/completions.py
adulib/llm/embeddings.py
adulib/llm/rate_limits.py
adulib/llm/text_completions.py
adulib/llm/tokens.py
adulib/utils/__init__.py
adulib/utils/base.py
adulib/utils/daemons.py
adulib/utils/pipes.py
adulib/utils/wrangle.py
adulib-0.4.5.dist-info/METADATA
adulib-0.4.5.dist-info/WHEEL
adulib-0.4.5.dist-info/licenses/LICENSE
adulib-0.4.5.dist-info/RECORD
