Metadata-Version: 2.4
Name: adulib
Version: 0.4.5
Summary: Tools and utilities developed by the Autonomy Data Unit (ADU).
Author-email: Lukas Kikuchi <lukas.kikuchi@gmail.com>
License-File: LICENSE
Requires-Python: >=3.9
Requires-Dist: aiohttp>=3.11.12
Requires-Dist: asynciolimiter>=1.0.0
Requires-Dist: diskcache>=5.6.3
Requires-Dist: fastcore>=1.8.2
Requires-Dist: pandas>=2.3.0
Requires-Dist: pipe>=2.2
Requires-Dist: pydantic>=2.10.6
Requires-Dist: pyperclip>=1.9.0
Requires-Dist: python-dotenv>=1.1.0
Requires-Dist: questionary>=2.1.0
Requires-Dist: tqdm>=4.67.1
Requires-Dist: watchdog>=6.0.0
Provides-Extra: algos
Requires-Dist: numpy>=2.0.2; extra == 'algos'
Requires-Dist: rapidfuzz>=3.13.0; extra == 'algos'
Requires-Dist: scikit-learn>=1.6.1; extra == 'algos'
Provides-Extra: llm
Requires-Dist: litellm>=1.67.5; extra == 'llm'
